{
	"data": [
		{ "id":1,"code":"CN8600463411","name":"FEDERACION COLOMBIANA DE PRODUCTORES DE PAPA FEDEPAPA ANT","nit":"860046341-5","jefezona":"Diego Alejandro Monsalve Bedoya","telefono":"","email":""},
        { "id":2,"code":"CN901242222","name":"LA CASA DEL AGRO MCU S.A.S","nit":"901242222-5","jefezona":"Diego Alejandro Monsalve Bedoya","telefono":"","email":""},
        { "id":3,"code":"CN70696427","name":"LUIS ALBERTO RODRIGUEZ GONZALEZ","nit":"70696427-2","jefezona":"Diego Alejandro Monsalve Bedoya","telefono":"","email":""},
        { "id":4,"code":"CN891201294","name":"COOPERATIVA DE PRODUCTOS LACTEOS NARIÑO LTDA","nit":"891201294-4","jefezona":"Eliana Elizabeth Patiño Rojas","telefono":"","email":""},
        { "id":5,"code":"CN805019457","name":"COOPERATIVA MULTIACTIVA UNIAGRO","nit":"805019457-6","jefezona":"Rodrigo Paredes Cabal","telefono":"","email":""},
        { "id":6,"code":"CN901584196","name":"AGRICO DISTRIBUIDORA Y CONSTRUCTORA SAS","nit":"901584196-9","jefezona":"Rodrigo Paredes Cabal","telefono":"","email":""},
        { "id":7,"code":"CN891200986","name":"COOPERATIVA DE CAFICULTORES DE OCCIDENTE DE NARIÑO  LTDA","nit":"891200986-8","jefezona":"Eliana Elizabeth Patiño Rojas","telefono":"","email":""},
        { "id":8,"code":"CN901264830","name":"AGROPECUARIA LA HACIENDA PUTUMAYO S.A.S ZOMAC","nit":"901264830-8","jefezona":"Eliana Elizabeth Patiño Rojas","telefono":"","email":""},
        { "id":9,"code":"CN12975282","name":"JAIRO ANTONIO ESPAÑA PAREDES","nit":"12975282-8","jefezona":"Eliana Elizabeth Patiño Rojas","telefono":"","email":""},
        { "id":10,"code":"CN891201428","name":"AGROGANADERO S.A.S EN PROCESO DE ORGANIZACIÓN","nit":"891201428-4","jefezona":"Eliana Elizabeth Patiño Rojas","telefono":"","email":""},
        { "id":11,"code":"CN900347805","name":"CAMPOFERT S.A.S","nit":"900347805-7","jefezona":"Rodrigo Paredes Cabal","telefono":"","email":""},
        { "id":12,"code":"CN900606950","name":"AGROFERTILIZANTES & CAFÉ SAS","nit":"900606950-9","jefezona":"Rodrigo Paredes Cabal","telefono":"","email":""},
        { "id":13,"code":"CN900321419","name":"GRUPO CENAGRO S.A.S","nit":"900321419-4","jefezona":"Rodrigo Paredes Cabal","telefono":"","email":""},
        { "id":14,"code":"CN890500571","name":"COOPERATIVA AGROPECUARIA DEL NORTE DE SANTANDER","nit":"890500571-9","jefezona":"Winston Moreno","telefono":"","email":""},
        { "id":15,"code":"CN890801106","name":"COOPERATIVA DE CAFICULTORES DEL ALTO OCCIDENTE DE CALDAS","nit":"890801106-9","jefezona":"Jaime Humberto Arias Rivera","telefono":"","email":""},
        { "id":16,"code":"CN805020771","name":"AGRICULTURA Y SERVICIOS S.A.S","nit":"805020771-6","jefezona":"Rodrigo Paredes Cabal","telefono":"","email":""},
        { "id":17,"code":"CN900155227","name":"FRUTY GREEN SAS","nit":"900155227-5","jefezona":"Jaime Humberto Arias Rivera","telefono":"","email":""},
        { "id":18,"code":"CN900534062","name":"DISAGRO DE OCCIDENTE SAS","nit":"900534062-3","jefezona":"Rodrigo Paredes Cabal","telefono":"","email":""},
        { "id":19,"code":"CN901377609","name":"AGRO MIL AGROS SAS","nit":"901377609-1","jefezona":"Diego Alejandro Monsalve Bedoya","telefono":"","email":""},
        { "id":20,"code":"CN901042166","name":"AGROZAM FACATATIVA SAS","nit":"901042166-2","jefezona":"Angela Liceth Pombo Castro","telefono":"","email":""},
        { "id":21,"code":"CN900315039","name":"GLOBALAGRO NEIVA S.A.S.","nit":"900315039-4","jefezona":"Manuel Fernando Covaleda Losada","telefono":"","email":""},
        { "id":22,"code":"CN900760898","name":"AGROJABA SAS","nit":"900760898-1","jefezona":"Rodrigo Paredes Cabal","telefono":"","email":""},
        { "id":23,"code":"CN891100321","name":"COOPERATIVA MULTIACTIVA AGROPECUARIA DEL HUILA COAGROHUILA","nit":"891100321-1","jefezona":"Manuel Fernando Covaleda Losada","telefono":"","email":""},
        { "id":24,"code":"CN890918965","name":"C.I.TECNICAS BALTIME DE COLOMBIA S.A.","nit":"890918965-2","jefezona":"Jorge Arteta","telefono":"","email":""},
        { "id":25,"code":"CN891500231","name":"COOPERATIVA DE CAFICULTORES DEL CAUCA","nit":"891500231-3","jefezona":"Rodrigo Paredes Cabal","telefono":"","email":""},
        { "id":26,"code":"CN83057759","name":"JAIRO ABEL ZAMBRANO CORDOBA","nit":"83057759-9","jefezona":"Manuel Fernando Covaleda Losada","telefono":"","email":""},
        { "id":27,"code":"CN834001328","name":"UNISANTANDER S.A.S.","nit":"834001328-0","jefezona":"Winston Moreno","telefono":"","email":""},
        { "id":28,"code":"CN901373646","name":"AGROCOMPANY GROUP SAS","nit":"901373646-6","jefezona":"Administrativo","telefono":"","email":""},
        { "id":29,"code":"CN900506620","name":"ABOCAR RISARALDA SAS","nit":"900506620-4","jefezona":"Jaime Humberto Arias Rivera","telefono":"","email":""},
        { "id":30,"code":"CN900230609","name":"DISTRIBUIDORA AGRICOLA LA COSECHA SAS","nit":"900230609-6","jefezona":"Eliana Elizabeth Patiño Rojas","telefono":"","email":""},
        { "id":31,"code":"CN901101007","name":"LOGYCAMPO SAS","nit":"901101007-3","jefezona":"Diego Alejandro Monsalve Bedoya","telefono":"","email":""},
        { "id":32,"code":"CN900829016","name":"ALMA-G S.A.S.","nit":"900829016-1","jefezona":"Manuel Fernando Covaleda Losada","telefono":"","email":""},
        { "id":33,"code":"CN2282230","name":"FIDEL MENDEZ REINOSO","nit":"2282230-4","jefezona":"Geovany Alexander Vanegas Guzman","telefono":"","email":""},
        { "id":34,"code":"CN901130868","name":"AHABAH AGRO S.A.S","nit":"901130868-1","jefezona":"Jaime Humberto Arias Rivera","telefono":"","email":""},
        { "id":35,"code":"CN901454500","name":"AGROPECUARIA LATORRE SAS","nit":"901454500-8","jefezona":"Winston Moreno","telefono":"","email":""},
        { "id":36,"code":"CN890900285","name":"COMPAÑIA DE EMPAQUES S.A","nit":"890900285-3","jefezona":"Administrativo","telefono":"","email":""},
        { "id":37,"code":"CN900837965","name":"DISTRIBUCIONES UNIVERSO AGRICOLAS S.A.S","nit":"900837965-1","jefezona":"Winston Moreno","telefono":"","email":""},
        { "id":38,"code":"CN16074567","name":"JULIO HERNANDO SEPULVEDA GALLEGO","nit":"16074567-1","jefezona":"Jaime Humberto Arias Rivera","telefono":"","email":""},
        { "id":39,"code":"CN8600075382","name":"FEDERACIÓN NACIONAL DE CAFETEROS DE COLOMBIA  CALDAS","nit":"860007538-2","jefezona":"Jaime Humberto Arias Rivera","telefono":"","email":""},
        { "id":40,"code":"CN91072539","name":"OSCAR VALDIVIESO VERGARA","nit":"91072539-7","jefezona":"Winston Moreno","telefono":"","email":""},
        { "id":41,"code":"CN890801626","name":"COOPERATIVA DE CAFICULTORES DE ANSERMA LTDA","nit":"890801626-7","jefezona":"Jaime Humberto Arias Rivera","telefono":"","email":""},
        { "id":42,"code":"CN1047967724","name":"MARINELA RESTREPO RAMIREZ","nit":"1047967724-6","jefezona":"Diego Alejandro Monsalve Bedoya","telefono":"","email":""},
        { "id":43,"code":"CN1114731061","name":"JAIRO VIVAS HENAO","nit":"1114731061-0","jefezona":"Rodrigo Paredes Cabal","telefono":"","email":""},
        { "id":44,"code":"CN901139195","name":"AGROVETERINARIA ADESUR SAS","nit":"901139195-4","jefezona":"Eliana Elizabeth Patiño Rojas","telefono":"","email":""},
        { "id":45,"code":"CN800094791","name":"FRUTERA DE SANTA MARTA SA","nit":"800094791-2","jefezona":"Jorge Arteta","telefono":"","email":""},
        { "id":46,"code":"CN891400088","name":"COOPERATIVA DEPARTAMENTAL DE CAFICULTORES DEL RISARALDA","nit":"891400088-7","jefezona":"Jaime Humberto Arias Rivera","telefono":"","email":""},
        { "id":47,"code":"CN811025861","name":"COOPERATIVA DE CAFICULTORES DE ANTIOQUIA LTDA","nit":"811025861-5","jefezona":"Juan Jacobo Castrillon","telefono":"","email":""},
        { "id":48,"code":"CN900405749","name":"BODEGA CAMPESINA S.A.S","nit":"900405749-1","jefezona":"Diego Alejandro Monsalve Bedoya","telefono":"","email":""},
        { "id":49,"code":"CN811034512","name":"COMERCIALIZADORA DEL CAMPO Y LA CONSTRUCCION  SAS","nit":"811034512-8","jefezona":"Juan Jacobo Castrillon","telefono":"","email":""},
        { "id":50,"code":"CN900396965","name":"AGROINDUSTRIAL DE PALMA ACEITERA S.A. SUCURSAL COLOMBIA","nit":"900396965-6","jefezona":"Raul  Barrera","telefono":"","email":""},
        { "id":51,"code":"CN901274170","name":"LA SEPTIMA DISTRIBUCIONES AGROPECUARIAS S.A.S","nit":"901274170-8","jefezona":"Winston Moreno","telefono":"","email":""},
        { "id":52,"code":"CN837000715","name":"CASA DEL GRANJERO S.A","nit":"837000715-4","jefezona":"Eliana Elizabeth Patiño Rojas","telefono":"","email":""},
        { "id":53,"code":"CN805020771","name":"AGRICULTURA Y SERVICIOS S.A.S","nit":"805020771-6","jefezona":"Jaime Humberto Arias Rivera","telefono":"","email":""},
        { "id":54,"code":"CN901207797","name":"C.I. FRUSAMA S.A.S.","nit":"901207797-1","jefezona":"Jorge Arteta","telefono":"","email":""},
        { "id":55,"code":"CN9957626","name":"NESTOR MAURICIO JIMENEZ LOAIZA","nit":"9957626-0","jefezona":"Jaime Humberto Arias Rivera","telefono":"","email":""},
        { "id":56,"code":"CN901279487","name":"AGROMAZORCA SAS PLANETA RICA","nit":"901279487-1","jefezona":"Rafael Antonio Burgos Fonseca","telefono":"","email":""},
        { "id":57,"code":"CN5913204","name":"LUIS EDUARDO DIAZ ARIAS","nit":"5913204-2","jefezona":"Geovany Alexander Vanegas Guzman","telefono":"","email":""},
        { "id":58,"code":"CN901386413","name":"EL CORRAL AGRO SAS  ZOMAC","nit":"901386413-3","jefezona":"Geovany Alexander Vanegas Guzman","telefono":"","email":""},
        { "id":59,"code":"CN809000555","name":"DIANA AGRICOLA S.A.S","nit":"809000555-0","jefezona":"Rafael Antonio Burgos Fonseca","telefono":"","email":""},
        { "id":60,"code":"CN5992943","name":"JOSE ALBEIRO ROJAS LOPEZ","nit":"5992943-4","jefezona":"Geovany Alexander Vanegas Guzman","telefono":"","email":""},
        { "id":61,"code":"CN21846981","name":"MARIA DORA LARA ARIAS","nit":"21846981-8","jefezona":"Diego Alejandro Monsalve Bedoya","telefono":"","email":""},
        { "id":62,"code":"CN900785534","name":"ANDINO AGRICOLA DEL EJE CAFETERO S.A.S.","nit":"900785534-4","jefezona":"Jaime Humberto Arias Rivera","telefono":"","email":""},
        { "id":63,"code":"CN8244359","name":"FRANCISCO URIEL GUERRA MEDINA","nit":"8244359-5","jefezona":"Diego Alejandro Monsalve Bedoya","telefono":"","email":""},
        { "id":64,"code":"CN901160182","name":"A.F CAFE S.A.S - ZOMAC","nit":"901160182-6","jefezona":"Geovany Alexander Vanegas Guzman","telefono":"","email":""},
        { "id":65,"code":"CN891102742","name":"INSUMOS HUILA S.A.S","nit":"891102742-8","jefezona":"Manuel Fernando Covaleda Losada","telefono":"","email":""},
        { "id":66,"code":"CN1090467514","name":"ROBINSON ALIRIO GUERRERO SUAREZ","nit":"1090467514-7","jefezona":"Winston Moreno","telefono":"","email":""},
        { "id":67,"code":"CN890701355","name":"COOPERATIVA SERVIARROZ LTDA","nit":"890701355-7","jefezona":"Geovany Alexander Vanegas Guzman","telefono":"","email":""},
        { "id":68,"code":"CN900974078","name":"AGROBOLIVAR SG S.A.S","nit":"900974078-8","jefezona":"Diego Alejandro Monsalve Bedoya","telefono":"","email":""},
        { "id":69,"code":"CN890300440","name":"CASTILLA AGRICOLA SA","nit":"890300440-4","jefezona":"Rodrigo Paredes Cabal","telefono":"","email":""},
        { "id":70,"code":"CN901242099","name":"AGROBOLIVAR FLOWERS S.A.S.","nit":"901242099-5","jefezona":"Diego Alejandro Monsalve Bedoya","telefono":"","email":""},
        { "id":71,"code":"CN70954447","name":"NORBEY ALEXANDER CANO DUQUE","nit":"70954447-7","jefezona":"Diego Alejandro Monsalve Bedoya","telefono":"","email":""},
        { "id":72,"code":"CN901148066","name":"DISTRUBUCIONES TIERRA FERTIL SAS","nit":"901148066-0","jefezona":"Winston Moreno","telefono":"","email":""},
        { "id":73,"code":"CN900197015","name":"INSUMOS AGROSERVILLA S.A.S.","nit":"900197015-0","jefezona":"Winston Moreno","telefono":"","email":""},
        { "id":74,"code":"CN891100445","name":"ORF S.A.","nit":"891100445-6","jefezona":"Raul  Barrera","telefono":"","email":""},
        { "id":75,"code":"CN1081728992","name":"CARLOS ALBERTO PEÑA VALENZUELA","nit":"1081728992-2","jefezona":"Manuel Fernando Covaleda Losada","telefono":"","email":""},
        { "id":76,"code":"CN901144703","name":"DISTRIBUIDORA EL PALMAR SAS ZOMAC","nit":"901144703-6","jefezona":"Paula Andrea Gonzalez Rico","telefono":"","email":""},
        { "id":77,"code":"CN891100296","name":"COOPERATIVA DEPARTAMENTAL DE CAFICULTORES DEL HUILA LTDA","nit":"891100296-5","jefezona":"Manuel Fernando Covaleda Losada","telefono":"","email":""},
        { "id":78,"code":"CN901417694","name":"CENTRAL DEL AGRO SAS","nit":"901417694-0","jefezona":"Manuel Fernando Covaleda Losada","telefono":"","email":""},
        { "id":79,"code":"CN860046341","name":"FEDERACION COLOMBIANA DE PRODUCTORES DE PAPA","nit":"860046341-5","jefezona":"Angela Liceth Pombo Castro","telefono":"","email":""},
        { "id":80,"code":"CN52833628","name":"NADIA JULIETH GALARZA LOZANO","nit":"52833628-9","jefezona":"Geovany Alexander Vanegas Guzman","telefono":"","email":""},
        { "id":81,"code":"CN900613466","name":"TERRA MIA M TM CIA S EN C","nit":"900613466-4","jefezona":"Angela Liceth Pombo Castro","telefono":"","email":""},
        { "id":82,"code":"CN2231659","name":"MANUEL OSWALDO PACHECO PRADILLA","nit":"2231659-1","jefezona":"Geovany Alexander Vanegas Guzman","telefono":"","email":""},
        { "id":83,"code":"CN38142161","name":"MAGDA ROCIO RUIZ MOLANO","nit":"38142161-5","jefezona":"Geovany Alexander Vanegas Guzman","telefono":"","email":""},
        { "id":84,"code":"CN3469254","name":"RAMON FERNANDO DE JESUS MONTOYA JARAMILLO","nit":"3469254-9","jefezona":"Diego Alejandro Monsalve Bedoya","telefono":"","email":""},
        { "id":85,"code":"CN900863582","name":"SUPERGRANOS DISTRIBUCIONES S.A.S","nit":"900863582-2","jefezona":"Rodrigo Paredes Cabal","telefono":"","email":""},
        { "id":86,"code":"CN900552192","name":"ROCHA PAEZ SAS","nit":"900552192-9","jefezona":"Winston Moreno","telefono":"","email":""},
        { "id":87,"code":"CN891400435","name":"COOPERATIVA DE CAFICULTORES SANTA ROSA DE CABAL LTDA","nit":"891400435-1","jefezona":"Jaime Humberto Arias Rivera","telefono":"","email":""},
        { "id":88,"code":"CN24683880","name":"MARIA LEONILA VELEZ DE HINCAPIE","nit":"24683880-2","jefezona":"Jaime Humberto Arias Rivera","telefono":"","email":""},
        { "id":89,"code":"CN890700058","name":"UNION DE ARROCEROS S.A.S","nit":"890700058-1","jefezona":"Geovany Alexander Vanegas Guzman","telefono":"","email":""},
        { "id":90,"code":"CN900539353","name":"AGROVETERINARIA LA FINQUITA DEL LLANO S. A. S","nit":"900539353-4","jefezona":"Paula Andrea Gonzalez Rico","telefono":"","email":""}


    ]
}