{
    "data": [
        {"id":"Stelle_2","name":"Centro general 2"},
        {"id":"THUMANO","name":"TALENTO HUMANO"},
        {"id":"PRESIDE2","name":"PRESIDENCIA"},
        {"id":"JURIDICA","name":"JURIDICA"},
        {"id":"PRCTROLP","name":"PROTECCION Y CONTROL PERDIDAS"},
        {"id":"CINTERNO","name":"CONTROL INTERNO"},
        {"id":"ASCORPOR","name":"ASUNTOS CORPORATIVOS"},
        {"id":"VPCADSU2","name":"VP CADENA DE SUMINISTROS"},
        {"id":"ADMINIST","name":"ADMINISTRATIVO"},
        {"id":"PROCURA","name":"PROCURA"},
        {"id":"CEXTERIO","name":"COMERCIO EXTERIOR"},
        {"id":"OINTCNAL","name":"OPERACIONES INTERNACIONALES"},
        {"id":"VPFINAN2","name":"VP FINANCIERA"},
        {"id":"CONTABIL","name":"CONTABILIDAD"},
        {"id":"TRIBUTAR","name":"TRIBUTARIO"},
        {"id":"PRESCOST","name":"PRESUPUESTOS Y COSTOS"},
        {"id":"TESORERI","name":"TESORERIA"},
        {"id":"MEDFINAN","name":"MEDIOS FINANCIACION"},
        {"id":"VPCOCIA2","name":"VP COMERCIAL"},
        {"id":"CCINORTE","name":"COMERCIAL NORTE"},
        {"id":"CCIALSUR","name":"COMERCIAL SUR"},
        {"id":"CCIAL360","name":"COMERCIAL 360"},
        {"id":"MERCADEO","name":"MERCADEO"},
        {"id":"VPOPERA2","name":"VP OPERACIONES"},
        {"id":"INFRAEST","name":"INFRAESTRUCTURA Y PROYECTOS"},
        {"id":"PRODCION","name":"PRODUCCION"},
        {"id":"LOGISTIC","name":"LOGISTICA"},
        {"id":"GPRODUCC","name":"GERENCIA PRODUCCIÓN"},
        {"id":"MANTEMTO","name":"MANTENIMIENTO"},
        {"id":"TECNOLOG","name":"TECNOLOGIA"},
        {"id":"COLECTO2","name":"COLECTOR"},
        {"id":"CCIADATI","name":"Desarrollo agron y tecnol inno"},
        {"id":"FUNDACIO","name":"Fundacion Nitrofert"},
        {"id":"SEGUROS","name":"SEGUROS"},
        {"id":"SERCLIEN","name":"SERVICIO AL CLIENTE"},
        {"id":"LOGOPER","name":"LOGISTICA OPERATIVA"},
        {"id":"VTAEXPOR","name":"VENTAS EXPORTACIONES"},
        {"id":"PROYECTO","name":"PROYECTOS"},
        {"id":"INNOVACI","name":"INNOVACION"},
        {"id":"ALMATERI","name":"ALMACEN DE MATERIALES"},
        {"id":"PLANCIAL","name":"PLANIFICACION COMERCIAL"},
        {"id":"VPCOCIAL","name":"VP COMERCIAL"}

    ]
}